toloka/common/http/__init__.py
toloka/common/http/args.py
toloka/common/http/auth/__init__.py
toloka/common/http/auth/apikey.py
toloka/common/http/auth/common.py
toloka/common/http/auth/jwt.py
toloka/common/http/client.py
toloka/common/http/defaults.py
toloka/common/http/py.typed
toloka_http-0.2.1.dist-info/WHEEL
toloka_http-0.2.1.dist-info/METADATA
toloka_http-0.2.1.dist-info/RECORD
