Metadata-Version: 2.1
Name: toloka_http
Requires-Python: >= 3.10
Requires-Dist: httpx[http2]
Requires-Dist: tenacity
Provides-Extra: jwt
Requires-Dist: toloka-common-jwt; extra == 'jwt'
Version: 0.2.1
